auto_requirements/__init__.py
auto_requirements/manager.py
auto_requirements-0.1.dist-info/LICENSE
auto_requirements-0.1.dist-info/METADATA
auto_requirements-0.1.dist-info/WHEEL
auto_requirements-0.1.dist-info/top_level.txt
auto_requirements-0.1.dist-info/RECORD
